proteoxystis/__init__.py
proteoxystis/protex.py
proteoxystis-0.0.1.dist-info/LICENSE
proteoxystis-0.0.1.dist-info/METADATA
proteoxystis-0.0.1.dist-info/WHEEL
proteoxystis-0.0.1.dist-info/entry_points.txt
proteoxystis-0.0.1.dist-info/RECORD
