Metadata-Version: 2.1
Name: proteoxystis
Version: 0.0.1
Summary: Minimal python project that exposes a commandline feature
Home-page: https://github.com/retospect/proteoxystis
License: GPL-3
Keywords: example
Author: Reto Stamm
Maintainer: Reto Stamm
Classifier: License :: Other/Proprietary License
Classifier: Programming Language :: Python :: 2
Classifier: Programming Language :: Python :: 2.7
Classifier: Programming Language :: Python :: 3
Classifier: Programming Language :: Python :: 3.4
Classifier: Programming Language :: Python :: 3.5
Classifier: Programming Language :: Python :: 3.6
Classifier: Programming Language :: Python :: 3.7
Classifier: Programming Language :: Python :: 3.8
Classifier: Programming Language :: Python :: 3.9
Classifier: Programming Language :: Python :: 3.10
Classifier: Programming Language :: Python :: 3.11
Classifier: Programming Language :: Python :: 3
Project-URL: Repository, https://github.com/retospect/proteoxystis
